orbital/__init__.py
orbital/orbital.py
sputnik_orbital-1.0.0.dist-info/DESCRIPTION.rst
sputnik_orbital-1.0.0.dist-info/METADATA
sputnik_orbital-1.0.0.dist-info/RECORD
sputnik_orbital-1.0.0.dist-info/WHEEL
sputnik_orbital-1.0.0.dist-info/metadata.json
sputnik_orbital-1.0.0.dist-info/top_level.txt
