Metadata-Version: 2.0
Name: sputnik-orbital
Version: 1.0.0
Summary: Distributed resources for another library with S3
Home-page: https://github.com/skimit/orbital
Author: Miroslav Batchkarov
Author-email: mbatchkarov@gmail.com
License: UNKNOWN
Platform: UNKNOWN
